astro_gdt_fermi-2.2.2.data/scripts/dol4.exe
astro_gdt_fermi-2.2.2.data/scripts/dol_source_angles.py
astro_gdt_fermi-2.2.2.dist-info/licenses/license.txt
gdt/data/fermi-gbm.urls
gdt/missions/fermi/__init__.py
gdt/missions/fermi/frame.py
gdt/missions/fermi/mcilwainl.py
gdt/missions/fermi/plot.py
gdt/missions/fermi/time.py
gdt/missions/fermi/data/McIlwainL_Coeffs.npy
gdt/missions/fermi/gbm/__init__.py
gdt/missions/fermi/gbm/catalogs.py
gdt/missions/fermi/gbm/classification.py
gdt/missions/fermi/gbm/collection.py
gdt/missions/fermi/gbm/detectors.py
gdt/missions/fermi/gbm/finders.py
gdt/missions/fermi/gbm/headers.py
gdt/missions/fermi/gbm/phaii.py
gdt/missions/fermi/gbm/poshist.py
gdt/missions/fermi/gbm/response.py
gdt/missions/fermi/gbm/saa.py
gdt/missions/fermi/gbm/scat.py
gdt/missions/fermi/gbm/tcat.py
gdt/missions/fermi/gbm/trigdat.py
gdt/missions/fermi/gbm/tte.py
gdt/missions/fermi/gbm/localization/__init__.py
gdt/missions/fermi/gbm/localization/dol/__init__.py
gdt/missions/fermi/gbm/localization/dol/legacy_dol.py
gdt/missions/fermi/gbm/localization/dol/legacy_functions.py
gdt/missions/fermi/gbm/localization/dol/legacy_spectral_models.py
gdt/missions/fermi/gbm/localization/dol/data/alocdat_comp.npy
gdt/missions/fermi/gbm/localization/dol/data/band_1deg_50_300_hard.npy
gdt/missions/fermi/gbm/localization/dol/data/band_1deg_50_300_norm.npy
gdt/missions/fermi/gbm/localization/dol/data/band_1deg_50_300_soft.npy
gdt/missions/fermi/gbm/localization/dol/data/band_1deg_5_50_soft.npy
gdt/missions/fermi/gbm/localization/dol/data/comp_1deg_50_300_hard.npy
gdt/missions/fermi/gbm/localization/dol/data/comp_1deg_50_300_norm.npy
gdt/missions/fermi/gbm/localization/dol/data/comp_1deg_50_300_soft.npy
gdt/missions/fermi/gbm/localization/dol/data/earth_points.npy
gdt/missions/fermi/gbm/trigger/__init__.py
gdt/missions/fermi/gbm/trigger/algorithms.py
gdt/missions/fermi/lat/__init__.py
astro_gdt_fermi-2.2.2.dist-info/METADATA
astro_gdt_fermi-2.2.2.dist-info/WHEEL
astro_gdt_fermi-2.2.2.dist-info/top_level.txt
astro_gdt_fermi-2.2.2.dist-info/RECORD
