Metadata-Version: 2.4
Name: astro-gdt-fermi
Version: 2.2.2
Summary: Gamma-ray Data Tools: Fermi Mission
Author: William Cleveland, Adam Goldstein, Daniel Kocevski
Author-email: STI-Software@usra.edu
License-Expression: Apache-2.0
Project-URL: Documentation, https://astro-gdt-fermi.readthedocs.io/en/latest/
Project-URL: Repository, https://github.com/USRA-STI/gdt-fermi
Project-URL: Issues, https://github.com/USRA-STI/gdt-fermi/issues
Keywords: astronomy,gammaray,gamma-ray,usra
Classifier: Development Status :: 5 - Production/Stable
Classifier: Programming Language :: Python :: 3
Classifier: Programming Language :: Python :: 3.11
Classifier: Operating System :: MacOS
Classifier: Operating System :: POSIX :: Linux
Classifier: Topic :: Scientific/Engineering :: Astronomy
Classifier: Topic :: Software Development :: Libraries
Requires-Python: >=3.11
License-File: license.txt
Requires-Dist: astro-gdt>=2.2.2
Provides-Extra: test
Requires-Dist: pytest; extra == "test"
Provides-Extra: docs
Requires-Dist: Sphinx==5.0.2; extra == "docs"
Requires-Dist: astropy-sphinx-theme; extra == "docs"
Requires-Dist: nbsphinx; extra == "docs"
Requires-Dist: sphinx-automodapi; extra == "docs"
Dynamic: license-file
